{
  "reported": [
    {
      "url": "https://weworkremotely.com/remote-jobs/ux-woman-entry-level-product-design-apprenticeship-1",
      "title": "Entry Level Product Design Apprenticeship",
      "company": "UX Woman",
      "score": 100,
      "date": "2026-05-29 10:58"
    },
    {
      "url": "https://weworkremotely.com/remote-jobs/blueprint-product-designer",
      "title": "Product Designer",
      "company": "Blueprint",
      "score": 100,
      "date": "2026-05-29 10:58"
    },
    {
      "url": "https://www.arbeitnow.com/jobs/companies/6pm-gmbh/corporate-graphic-designer-frankfurt-am-main-254896",
      "title": "Corporate Graphic Designer (m/w/d)",
      "company": "6PM GmbH",
      "score": 87,
      "date": "2026-05-29 10:58"
    },
    {
      "url": "https://weworkremotely.com/remote-jobs/petra-brands-product-designer",
      "title": "Product Designer",
      "company": "Petra Brands",
      "score": 87,
      "date": "2026-05-29 10:58"
    },
    {
      "url": "https://jobicy.com/jobs/144244-founding-designer-americas",
      "title": "Founding Designer (Americas)",
      "company": "infisical",
      "score": 85,
      "date": "2026-05-29 10:58"
    },
    {
      "url": "https://jobicy.com/jobs/143456-associate-product-designer",
      "title": "Associate Product Designer",
      "company": "World Wide Technology",
      "score": 85,
      "date": "2026-05-29 10:58"
    },
    {
      "url": "https://jobicy.com/jobs/143375-junior-ui-designer-marketing-team",
      "title": "Junior UI designer (Marketing team)",
      "company": "TechMagic",
      "score": 85,
      "date": "2026-05-29 10:58"
    },
    {
      "url": "https://remoteOK.com/remote-jobs/remote-product-designer-south-geeks-1132403",
      "title": "Product Designer",
      "company": "South Geeks",
      "score": 82,
      "date": "2026-05-29 10:58"
    },
    {
      "url": "https://weworkremotely.com/remote-jobs/contra-graphic-designer-5",
      "title": "Graphic Designer",
      "company": "Contra",
      "score": 82,
      "date": "2026-05-29 10:58"
    },
    {
      "url": "https://www.arbeitnow.com/jobs/companies/bee-seen-agency/canva-designer-fur-social-media-grafiken-cologne-262371",
      "title": "Canva Designer für Social Media Grafiken (m/w/d)",
      "company": "Bee Seen Agency",
      "score": 72,
      "date": "2026-05-29 10:58"
    },
    {
      "url": "https://remoteOK.com/remote-jobs/remote-designer-indrive-1132472",
      "title": "Designer",
      "company": "inDrive",
      "score": 72,
      "date": "2026-05-29 10:58"
    },
    {
      "url": "https://remoteOK.com/remote-jobs/remote-graphic-designer-gamdom-1132426",
      "title": "Graphic Designer",
      "company": "Gamdom",
      "score": 72,
      "date": "2026-05-29 10:58"
    },
    {
      "url": "https://remoteOK.com/remote-jobs/remote-product-designer-designmeshai-1132393",
      "title": "Product Designer",
      "company": "DesignMeshAI",
      "score": 72,
      "date": "2026-05-29 10:58"
    },
    {
      "url": "https://remoteOK.com/remote-jobs/remote-product-designer-heidi-1132448",
      "title": "Product Designer",
      "company": "Heidi",
      "score": 72,
      "date": "2026-05-29 10:58"
    },
    {
      "url": "https://jobicy.com/jobs/144330-motion-designer-contractor",
      "title": "Motion Designer (Contractor)",
      "company": "Fortis Games",
      "score": 72,
      "date": "2026-05-29 10:58"
    },
    {
      "url": "https://jobicy.com/jobs/143763-conversational-designer",
      "title": "Conversational Designer",
      "company": "Cresta",
      "score": 72,
      "date": "2026-05-29 10:58"
    },
    {
      "url": "https://jobicy.com/jobs/143683-professional-application-designer",
      "title": "Professional Application Designer",
      "company": "Gainwell Technologies",
      "score": 72,
      "date": "2026-05-29 10:58"
    },
    {
      "url": "https://jobicy.com/jobs/143624-ui-ux-designer",
      "title": "UI/UX Designer",
      "company": "ManTech",
      "score": 72,
      "date": "2026-05-29 10:58"
    },
    {
      "url": "https://jobicy.com/jobs/143623-instructional-designer",
      "title": "Instructional Designer",
      "company": "LastPass",
      "score": 72,
      "date": "2026-05-29 10:58"
    },
    {
      "url": "https://weworkremotely.com/remote-jobs/nabu-global-fze-creative-performance-designer",
      "title": "Creative Performance Designer",
      "company": "Nabu Global FZE",
      "score": 72,
      "date": "2026-05-29 10:58"
    },
    {
      "url": "https://weworkremotely.com/remote-jobs/xm-turkish-speaking-video-motion-graphics-designer",
      "title": "Turkish-Speaking Video & Motion Graphics Designer",
      "company": "XM",
      "score": 72,
      "date": "2026-05-29 10:58"
    },
    {
      "url": "https://weworkremotely.com/remote-jobs/contra-brand-designer-7",
      "title": "Brand Designer",
      "company": "Contra",
      "score": 72,
      "date": "2026-05-29 10:58"
    },
    {
      "url": "https://weworkremotely.com/remote-jobs/contra-product-designer-5",
      "title": "Product Designer",
      "company": "Contra",
      "score": 72,
      "date": "2026-05-29 10:58"
    },
    {
      "url": "https://www.arbeitnow.com/jobs/companies/prematch/visual-designer-social-motion-cologne-75725",
      "title": "Visual Designer - Social & Motion (m/w/d)",
      "company": "Prematch",
      "score": 87,
      "date": "2026-05-29 12:45"
    },
    {
      "url": "https://www.arbeitnow.com/jobs/companies/joy/ui-ux-designer-berlin-478152",
      "title": "UI/UX Designer (m/f/d)",
      "company": "Joy_",
      "score": 77,
      "date": "2026-05-29 19:55"
    },
    {
      "url": "https://himalayas.app/companies/flummox/jobs/e-commerce-graphic-designer-part-time-remote-first-online-brand-house",
      "title": "E-COMMERCE GRAPHIC DESIGNER (PART-TIME, REMOTE-FIRST) @ ONLINE BRAND HOUSE",
      "company": "Flummox",
      "score": 87,
      "date": "2026-05-30 09:05"
    },
    {
      "url": "https://himalayas.app/companies/rezilient-health/jobs/marketing-design-specialist",
      "title": "Marketing Design Specialist",
      "company": "Rezilient Health",
      "score": 82,
      "date": "2026-05-30 09:05"
    },
    {
      "url": "https://www.arbeitnow.com/jobs/companies/edubini-gmbh/graphic-designer-hamburg-39510",
      "title": "Graphic Designer (m/w/d)",
      "company": "Edubini GmbH",
      "score": 77,
      "date": "2026-05-30 14:49"
    },
    {
      "url": "https://remoteOK.com/remote-jobs/remote-digital-designer-colibrix-one-1132593",
      "title": "Digital Designer",
      "company": "COLIBRIX ONE",
      "score": 77,
      "date": "2026-05-30 14:49"
    },
    {
      "url": "https://remoteOK.com/remote-jobs/remote-designer-thorne-1132610",
      "title": "Designer",
      "company": "Thorne",
      "score": 82,
      "date": "2026-05-30 22:33"
    },
    {
      "url": "https://himalayas.app/companies/pavago/jobs/ux-ui-designer-5126015865",
      "title": "UX/UI Designer",
      "company": "name",
      "score": 82,
      "date": "2026-05-30 22:33"
    },
    {
      "url": "https://www.arbeitnow.com/jobs/companies/migrando-gmbh/mediengestalter-web-digital-cottbus-45554",
      "title": "Mediengestalter Web & Digital (w/m/d)",
      "company": "Migrando GmbH",
      "score": 87,
      "date": "2026-06-01 19:30"
    },
    {
      "url": "https://www.arbeitnow.com/jobs/companies/migrando-gmbh/ui-ux-designer-cottbus-398585",
      "title": "UI/UX Designer (w/m/d)",
      "company": "Migrando GmbH",
      "score": 72,
      "date": "2026-06-01 19:30"
    },
    {
      "url": "https://www.arbeitnow.com/jobs/companies/ett-verpackungstechnik-gmbh/grafikdesigner-maschinen-technik-moringen-93852",
      "title": "Grafikdesigner (m/w/d) Maschinen & Technik",
      "company": "ETT Verpackungstechnik GmbH",
      "score": 100,
      "date": "2026-06-02 11:54"
    },
    {
      "url": "https://remoteOK.com/remote-jobs/remote-junior-brand-designer-twine-1132655",
      "title": "Junior Brand Designer",
      "company": "Twine",
      "score": 85,
      "date": "2026-06-02 11:54"
    },
    {
      "url": "https://www.arbeitnow.com/jobs/companies/bodengluck/grafikerin-fur-e-commerce-in-voll-oder-teilzeit-cologne-352266",
      "title": "Grafiker:in für E-Commerce in Voll- oder Teilzeit (m/w/d)",
      "company": "Bodenglück",
      "score": 82,
      "date": "2026-06-02 11:54"
    },
    {
      "url": "https://www.arbeitnow.com/jobs/companies/rudelkonig-gmbh/mediengestalter-grafikdesigner-teilzeit-30h-nuremberg-134441",
      "title": "Mediengestalter / Grafikdesigner (m/w/d) - Teilzeit (30h)",
      "company": "Rudelkönig GmbH",
      "score": 77,
      "date": "2026-06-02 11:54"
    },
    {
      "url": "https://weworkremotely.com/remote-jobs/mailerlite-graphic-designer",
      "title": "Graphic Designer",
      "company": "MailerLite",
      "score": 77,
      "date": "2026-06-02 11:54"
    },
    {
      "url": "https://www.arbeitnow.com/jobs/companies/migrando-gmbh/webdesigner-cottbus-52186",
      "title": "Webdesigner (w/m/d)",
      "company": "Migrando GmbH",
      "score": 72,
      "date": "2026-06-02 11:54"
    },
    {
      "url": "https://www.arbeitnow.com/jobs/companies/facts-and-fiction-gmbh/kommunikationsdesignerin-mit-dem-schwerpunkt-ux-design-in-koln-cologne-138440",
      "title": "Kommunikationsdesigner*in mit dem Schwerpunkt UX-Design in Köln (m/w/d)",
      "company": "facts and fiction GmbH",
      "score": 82,
      "date": "2026-06-02 22:07"
    },
    {
      "url": "https://remoteOK.com/remote-jobs/remote-creative-designer-air-apps-1132755",
      "title": "Creative Designer",
      "company": "Air Apps",
      "score": 87,
      "date": "2026-06-03 16:03"
    },
    {
      "url": "https://www.arbeitnow.com/jobs/companies/maintea-gmbh/grafikerin-all-genders-vollzeit-ab-august-frankfurt-am-main-198231",
      "title": "Grafiker:in (all genders) // Vollzeit // ab August // Frankfurt am Main",
      "company": "MainTea GmbH",
      "score": 82,
      "date": "2026-06-03 16:03"
    },
    {
      "url": "https://www.arbeitnow.com/jobs/companies/progyny-global/product-designer-ux-ui-berlin-246881",
      "title": "Product Designer (UX/UI) (m/f/x)",
      "company": "Progyny Global",
      "score": 77,
      "date": "2026-06-03 16:03"
    },
    {
      "url": "https://himalayas.app/companies/algaecal/jobs/intermediate-graphic-designer-6213853430",
      "title": "Intermediate Graphic Designer",
      "company": "AlgaeCal",
      "score": 82,
      "date": "2026-06-03 23:17"
    },
    {
      "url": "https://www.arbeitnow.com/jobs/companies/valorbyte-ug-haftungsbeschrankt/ui-ux-designer-karlsruhe-417466",
      "title": "UI/UX Designer",
      "company": "Valorbyte UG (haftungsbeschränkt)",
      "score": 77,
      "date": "2026-06-04 19:37"
    },
    {
      "url": "https://himalayas.app/companies/gannett-fleming-inc/jobs/vertical-transportation-designer",
      "title": "Vertical Transportation Designer",
      "company": "Gannett Fleming, Inc.",
      "score": 87,
      "date": "2026-06-04 23:56"
    },
    {
      "url": "https://remoteOK.com/remote-jobs/remote-product-designer-nevis-1132791",
      "title": "Product Designer",
      "company": "Nevis",
      "score": 77,
      "date": "2026-06-04 23:56"
    },
    {
      "url": "https://jobicy.com/jobs/145546-designer-web-presence-platform",
      "title": "Designer, Web Presence & Platform",
      "company": "Stripe",
      "score": 72,
      "date": "2026-06-05 11:52"
    },
    {
      "url": "https://remoteOK.com/remote-jobs/remote-junior-digital-designer-the-big-table-group-1132848",
      "title": "Junior Digital Designer",
      "company": "The Big Table Group",
      "score": 90,
      "date": "2026-06-05 22:48"
    },
    {
      "url": "https://www.arbeitnow.com/jobs/companies/neolymp/grafikdesigner-ki-designautomatisierung-berlin-183312",
      "title": "Grafikdesigner (m/w/d) - KI & Designautomatisierung",
      "company": "Neolymp",
      "score": 77,
      "date": "2026-06-05 22:48"
    },
    {
      "url": "https://weworkremotely.com/remote-jobs/lyncas-ux-designer-design-system-pleno",
      "title": "UX Designer – Design System Pleno",
      "company": "Lyncas",
      "score": 72,
      "date": "2026-06-05 22:48"
    },
    {
      "url": "https://himalayas.app/companies/omaze-company/jobs/contract-designer-4-months",
      "title": "Contract Designer (4 months)",
      "company": "name",
      "score": 72,
      "date": "2026-06-06 20:47"
    },
    {
      "url": "https://www.arbeitnow.com/jobs/companies/buzil-werk-wagner-gmbh-co-kg/mediengestalter-memmingen-223473",
      "title": "Mediengestalter (m/w/d)",
      "company": "BUZIL-WERK Wagner GmbH & Co. KG",
      "score": 87,
      "date": "2026-06-07 08:38"
    },
    {
      "url": "https://www.arbeitnow.com/jobs/companies/nuvallo/junior-graphic-designer-berlin-46044",
      "title": "Junior Graphic Designer (m/w/d)",
      "company": "nuvallo",
      "score": 85,
      "date": "2026-06-07 15:12"
    },
    {
      "url": "https://remoteOK.com/remote-jobs/remote-multi-grade-geographically-position-school-district-no-27-1132973",
      "title": "Multi Grade Geographically Position",
      "company": "School District No. 27",
      "score": 90,
      "date": "2026-06-07 20:02"
    },
    {
      "url": "https://himalayas.app/companies/renewed-vision/jobs/ux-designer-i-ii",
      "title": "UX Designer I / II",
      "company": "Renewed Vision",
      "score": 85,
      "date": "2026-06-07 20:02"
    },
    {
      "url": "https://remoteOK.com/remote-jobs/remote-graphic-narrator-resilient-solutions-plus-llc-1132981",
      "title": "Graphic Narrator",
      "company": "Resilient Solutions Plus, LLC",
      "score": 87,
      "date": "2026-06-08 12:47"
    },
    {
      "url": "https://himalayas.app/companies/kirin/jobs/remote-graphics-designer-output-based-hourly-7812245033",
      "title": "Remote - Graphics Designer - Output Based/Hourly",
      "company": "Kirin",
      "score": 82,
      "date": "2026-06-08 12:47"
    },
    {
      "url": "https://www.arbeitnow.com/jobs/companies/lyniq-studio/3d-designerin-in-voll-oder-teilzeit-c4d-redshift-bielefeld-322884",
      "title": "3D-DesignerIn (m/w/d) in Voll- oder Teilzeit - C4D & Redshift",
      "company": "LYNIQ STUDIO",
      "score": 72,
      "date": "2026-06-08 21:15"
    },
    {
      "url": "https://www.arbeitnow.com/jobs/companies/dfki-gmbh-robotics-innovation-center/studentische-hilfskraft-x-fur-grafik-foto-und-videoarbeiten-bremen-311395",
      "title": "Studentische Hilfskraft (m/w/d/x) für Grafik, Foto- und Videoarbeiten",
      "company": "DFKI GmbH - Robotics Innovation Center",
      "score": 72,
      "date": "2026-06-08 21:15"
    },
    {
      "url": "https://www.arbeitnow.com/jobs/companies/curia-consulting-gmbh/performance-creative-designer-dusseldorf-447331",
      "title": "Performance Creative Designer (m/w/d)",
      "company": "Curia Consulting GmbH",
      "score": 72,
      "date": "2026-06-09 10:43"
    },
    {
      "url": "https://www.arbeitnow.com/jobs/companies/bam-communication-gmbh/junior-graphic-designer-vollzeit-2-jahre-erfahrung-ab-sofort-berlin-214123",
      "title": "Junior Graphic Designer (m/w/d) (Vollzeit/ +2 Jahre Erfahrung/ ab sofort)",
      "company": "BAM Communication GmbH",
      "score": 100,
      "date": "2026-06-09 18:33"
    },
    {
      "url": "https://www.arbeitnow.com/jobs/companies/invivo-industrial-design/produkt-industriedesignerin-berlin-363598",
      "title": "Produkt-/Industriedesigner*in",
      "company": "invivo industrial design",
      "score": 90,
      "date": "2026-06-09 18:33"
    },
    {
      "url": "https://www.arbeitnow.com/jobs/companies/1komma50/mediengestalterin-hamburg-187706",
      "title": "Mediengestalter:in (m/w/d)",
      "company": "1KOMMA5˚",
      "score": 82,
      "date": "2026-06-09 18:33"
    },
    {
      "url": "https://remoteOK.com/remote-jobs/remote-web-designer-regex-seo-1133051",
      "title": "Web Designer",
      "company": "Regex SEO",
      "score": 72,
      "date": "2026-06-10 12:40"
    },
    {
      "url": "https://remoteOK.com/remote-jobs/remote-instructional-designer-bluefield-university-1133145",
      "title": "Instructional Designer",
      "company": "Bluefield University",
      "score": 72,
      "date": "2026-06-10 12:40"
    },
    {
      "url": "https://www.arbeitnow.com/jobs/companies/walts-comic-shop/graphic-designer-print-digital-part-time-15-20-hours-week-berlin-385688",
      "title": "Graphic Designer (Print & Digital) -  Part-Time (15 - 20 Hours/Week) (m/w/d)",
      "company": "Walt's Comic Shop",
      "score": 87,
      "date": "2026-06-10 21:28"
    },
    {
      "url": "https://www.arbeitnow.com/jobs/companies/walts-comic-shop/grafikdesignerin-teilzeit-15-20-stunden-woche-berlin-161551",
      "title": "Grafikdesigner:in - Teilzeit 15-20 Stunden/ Woche (m/w/d)",
      "company": "Walt's Comic Shop",
      "score": 87,
      "date": "2026-06-10 21:29"
    },
    {
      "url": "https://remoteOK.com/remote-jobs/remote-designer-ted-conferences-1133078",
      "title": "Designer",
      "company": "TED Conferences",
      "score": 87,
      "date": "2026-06-10 21:29"
    },
    {
      "url": "https://remoteOK.com/remote-jobs/remote-product-designer-butter-1133097",
      "title": "Product Designer",
      "company": "Butter",
      "score": 77,
      "date": "2026-06-10 21:29"
    },
    {
      "url": "https://remoteOK.com/remote-jobs/remote-brand-designer-canals-1133104",
      "title": "Brand Designer",
      "company": "Canals",
      "score": 72,
      "date": "2026-06-10 21:29"
    },
    {
      "url": "https://jobicy.com/jobs/146211-autodesk-civil-3d-designer",
      "title": "Autodesk Civil 3D Designer",
      "company": "EquipmentShare",
      "score": 72,
      "date": "2026-06-11 21:31"
    },
    {
      "url": "https://www.arbeitnow.com/jobs/companies/bearpaw-gmbh/grafiker-brand-designer-teilzeit-20-30h-bamberg-303463",
      "title": "Grafiker / Brand Designer (m/w/d) - Teilzeit 20-30h",
      "company": "Bearpaw GmbH",
      "score": 87,
      "date": "2026-06-12 11:54"
    },
    {
      "url": "https://remoteOK.com/remote-jobs/remote-junior-web-designer-infuse-1133315",
      "title": "Junior Web Designer",
      "company": "INFUSE",
      "score": 85,
      "date": "2026-06-12 11:54"
    },
    {
      "url": "https://remoteOK.com/remote-jobs/remote-brand-designer-project-twine-1133404",
      "title": "Brand Designer Project",
      "company": "Twine",
      "score": 72,
      "date": "2026-06-15 16:22"
    },
    {
      "url": "https://www.arbeitnow.com/jobs/companies/projektron-gmbh/mediengestaltung-grafikdesign-berlin-391272",
      "title": "Mediengestaltung / Grafikdesign",
      "company": "Projektron GmbH",
      "score": 87,
      "date": "2026-06-15 23:17"
    },
    {
      "url": "https://www.arbeitnow.com/jobs/companies/bugaga-werbeagentur-ek/mediengestalter-in-digital-und-print-mwd-hamburg-84636",
      "title": "Mediengestalter/in Digital und Print (mwd)",
      "company": "Bugaga Werbeagentur e.K.",
      "score": 87,
      "date": "2026-06-16 18:13"
    },
    {
      "url": "https://jobicy.com/jobs/146718-product-designer-5",
      "title": "Product Designer",
      "company": "Pogo",
      "score": 72,
      "date": "2026-06-16 18:13"
    },
    {
      "url": "https://remoteOK.com/remote-jobs/remote-graphic-designer-the-fountain-group-1133453",
      "title": "Graphic Designer",
      "company": "The Fountain Group",
      "score": 82,
      "date": "2026-06-16 23:55"
    },
    {
      "url": "https://jobicy.com/jobs/146920-surfacing-designer",
      "title": "Surfacing Designer",
      "company": "Meta",
      "score": 72,
      "date": "2026-06-16 23:55"
    },
    {
      "url": "https://www.arbeitnow.com/jobs/companies/bitsbirds-gmbh/grafikdesignerin-passau-468341",
      "title": "Grafikdesigner:in",
      "company": "bits&birds GmbH",
      "score": 87,
      "date": "2026-06-17 13:02"
    },
    {
      "url": "https://himalayas.app/companies/vald/jobs/digital-designer",
      "title": "Digital Designer",
      "company": "VALD",
      "score": 72,
      "date": "2026-06-17 13:02"
    },
    {
      "url": "https://remoteOK.com/remote-jobs/remote-product-designer-design-systems-penn-interactive-1133499",
      "title": "Product Designer Design Systems",
      "company": "Penn Interactive",
      "score": 72,
      "date": "2026-06-17 21:24"
    },
    {
      "url": "https://jobicy.com/jobs/147053-electrical-designer",
      "title": "Electrical Designer",
      "company": "ManTech",
      "score": 72,
      "date": "2026-06-17 21:24"
    },
    {
      "url": "https://www.arbeitnow.com/jobs/companies/invia-flights-germany-gmbh/design-system-designer-fluegede-leipzig-307228",
      "title": "Design System Designer  (m/w/d) / fluege.de",
      "company": "Invia Flights Germany GmbH",
      "score": 77,
      "date": "2026-06-18 11:57"
    },
    {
      "url": "https://remoteOK.com/remote-jobs/remote-junior-project-designer-archinect-1133677",
      "title": "Junior Project Designer",
      "company": "Archinect",
      "score": 85,
      "date": "2026-06-18 20:42"
    },
    {
      "url": "https://www.arbeitnow.com/jobs/companies/api-gmbh/kommunikationsdesigner-online-und-print-baesweiler-52294",
      "title": "Kommunikationsdesigner (m/w/d) Online und Print",
      "company": "api GmbH",
      "score": 82,
      "date": "2026-06-18 20:42"
    },
    {
      "url": "https://www.arbeitnow.com/jobs/companies/api-gmbh/mediengestalter-online-und-print-baesweiler-13286",
      "title": "Mediengestalter (m/w/d) Online und Print",
      "company": "api GmbH",
      "score": 82,
      "date": "2026-06-18 20:42"
    },
    {
      "url": "https://remoteOK.com/remote-jobs/remote-designer-newsquest-media-group-1133546",
      "title": "Designer",
      "company": "Newsquest Media Group",
      "score": 82,
      "date": "2026-06-18 20:42"
    },
    {
      "url": "https://www.arbeitnow.com/jobs/companies/agido-gmbh/digital-designer-fur-sportcontent-dortmund-108704",
      "title": "Digital Designer für Sportcontent (w/m/d)",
      "company": "agido GmbH",
      "score": 87,
      "date": "2026-06-19 12:33"
    },
    {
      "url": "https://remoteOK.com/remote-jobs/remote-social-content-designer-producer-josie-maran-1133579",
      "title": "Social Content Designer & Producer",
      "company": "Josie Maran",
      "score": 72,
      "date": "2026-06-19 12:33"
    },
    {
      "url": "https://www.arbeitnow.com/jobs/companies/geo-fennel-gmbh/mediengestalter-grafikdesigner-marketing-baunatal-11646",
      "title": "Mediengestalter / Grafikdesigner Marketing (m/w/d)",
      "company": "geo-FENNEL GmbH",
      "score": 82,
      "date": "2026-06-19 19:15"
    },
    {
      "url": "https://remoteOK.com/remote-jobs/remote-graphic-designer-swoon-1133676",
      "title": "Graphic Designer",
      "company": "Swoon",
      "score": 72,
      "date": "2026-06-19 19:16"
    },
    {
      "url": "https://himalayas.app/companies/great-minds/jobs/sr-graphic-designer",
      "title": "Sr Graphic Designer",
      "company": "Great Minds",
      "score": 87,
      "date": "2026-06-20 10:15"
    },
    {
      "url": "https://remoteOK.com/remote-jobs/remote-junior-graphic-designer-work-force-nexus-1133696",
      "title": "Junior Graphic Designer",
      "company": "Work Force Nexus",
      "score": 85,
      "date": "2026-06-20 10:15"
    },
    {
      "url": "https://himalayas.app/companies/bwise-media-ag/jobs/graphic-designer-m-f-x",
      "title": "Graphic Designer (m/f/x)",
      "company": "bwise Media AG",
      "score": 77,
      "date": "2026-06-20 10:15"
    }
  ]
}